[
  {"continent":"Africa","region":"North Africa","difficulty":"easy","question":"Which ancient civilization built the pyramids at Giza?","choices":["Ancient Egypt","Carthage","Nubia","Axum"],"answer":"Ancient Egypt"},
  {"continent":"Africa","region":"West Africa","difficulty":"easy","question":"Which empire was famous for its wealth in gold and was located in present-day Mali?","choices":["Mali Empire","Songhai Empire","Ghana Empire","Meroe Kingdom"],"answer":"Mali Empire"},
  {"continent":"Africa","region":"East Africa","difficulty":"medium","question":"Which ancient trading city on the Swahili coast became wealthy through trade with Arabia and India?","choices":["Kilwa","Cairo","Mompox","Zanzibar"],"answer":"Kilwa"},
  {"continent":"Africa","region":"Southern Africa","difficulty":"medium","question":"Who led the Zulu people to create a powerful kingdom in the early 19th century?","choices":["Shaka","Mansa Musa","Nelson","Lalibela"],"answer":"Shaka"},
  {"continent":"Africa","region":"North Africa","difficulty":"hard","question":"Which Carthaginian general famously crossed the Alps to invade Italy during the Second Punic War?","choices":["Hannibal","Scipio","Hasdrubal","Mago"],"answer":"Hannibal"},
  {"continent":"Africa","region":"East Africa","difficulty":"hard","question":"Which medieval Ethiopian king is traditionally associated with the rock-hewn churches of Lalibela?","choices":["Gebre Mesqel Lalibela","Haile Selassie","Ezana","Menelik II"],"answer":"Gebre Mesqel Lalibela"},

  {"continent":"Asia","region":"East Asia","difficulty":"easy","question":"Which dynasty built the majority of the Great Wall of China that we see today?","choices":["Ming","Han","Tang","Qin"],"answer":"Ming"},
  {"continent":"Asia","region":"South Asia","difficulty":"easy","question":"Which empire is known for spreading Buddhism across much of South Asia and beyond under Emperor Ashoka?","choices":["Maurya Empire","Gupta Empire","Mughal Empire","Chola Empire"],"answer":"Maurya Empire"},
  {"continent":"Asia","region":"Southeast Asia","difficulty":"medium","question":"Which Khmer temple complex in present-day Cambodia is the largest religious monument in the world?","choices":["Angkor Wat","Borobudur","Bagan","Ayutthaya"],"answer":"Angkor Wat"},
  {"continent":"Asia","region":"Central Asia","difficulty":"medium","question":"Which leader created a vast empire across Asia in the 13th century, known for his horse-mounted armies?","choices":["Genghis Khan","Tamerlane","Kublai Khan","Nader Shah"],"answer":"Genghis Khan"},
  {"continent":"Asia","region":"East Asia","difficulty":"hard","question":"Which Japanese period (1185–1333) is marked by the dominance of samurai and the establishment of the first shogunate?","choices":["Kamakura period","Heian period","Azuchi–Momoyama","Muromachi period"],"answer":"Kamakura period"},
  {"continent":"Asia","region":"South Asia","difficulty":"hard","question":"Which Persian origin dynasty established the Mughal Empire in India in the 16th century?","choices":["Babur's dynasty","Safavid","Ottoman","Maurya"],"answer":"Babur's dynasty"},

  {"continent":"Europe","region":"Western Europe","difficulty":"easy","question":"Which event in 1066 led to Norman rule in England?","choices":["Battle of Hastings","Magna Carta","Great Fire of London","English Civil War"],"answer":"Battle of Hastings"},
  {"continent":"Europe","region":"Eastern Europe","difficulty":"easy","question":"Which empire was ruled by tsars and ended after the 1917 revolution?","choices":["Russian Empire","Ottoman Empire","Austro-Hungarian Empire","Byzantine Empire"],"answer":"Russian Empire"},
  {"continent":"Europe","region":"Southern Europe","difficulty":"medium","question":"Which ancient civilization famously built the Colosseum and aqueducts?","choices":["Roman Empire","Greek City-States","Etruscans","Byzantium"],"answer":"Roman Empire"},
  {"continent":"Europe","region":"Northern Europe","difficulty":"medium","question":"Which seafaring Norse people explored and settled Iceland, Greenland, and reached North America?","choices":["Vikings","Huns","Saxons","Franks"],"answer":"Vikings"},
  {"continent":"Europe","region":"Western Europe","difficulty":"hard","question":"Which treaty signed in 1648 ended the Thirty Years' War and helped establish the modern state system in Europe?","choices":["Peace of Westphalia","Treaty of Versailles","Treaty of Utrecht","Treaty of Tordesillas"],"answer":"Peace of Westphalia"},
  {"continent":"Europe","region":"Eastern Europe","difficulty":"hard","question":"Which medieval empire preserved much of Roman law and Greek scholarship in its capital, Constantinople?","choices":["Byzantine Empire","Holy Roman Empire","Ottoman Empire","Kievan Rus'"],"answer":"Byzantine Empire"},

  {"continent":"North America","region":"Caribbean & Central America","difficulty":"easy","question":"Which civilization built the stepped pyramids at Chichén Itzá?","choices":["Maya","Aztec","Inca","Olmec"],"answer":"Maya"},
  {"continent":"North America","region":"Mesoamerica","difficulty":"easy","question":"Which empire had its capital at Tenochtitlán before Spanish conquest?","choices":["Aztec","Maya","Inca","Toltec"],"answer":"Aztec"},
  {"continent":"North America","region":"United States","difficulty":"medium","question":"Which document, adopted in 1776, declared independence from Britain?","choices":["Declaration of Independence","Bill of Rights","Federalist Papers","Magna Carta"],"answer":"Declaration of Independence"},
  {"continent":"North America","region":"Canada","difficulty":"medium","question":"Which Indigenous polity in the Great Lakes region formed a confederacy known as the Iroquois or Haudenosaunee?","choices":["The Iroquois Confederacy","The Aztec League","The Cherokee Nation","The Sioux Alliance"],"answer":"The Iroquois Confederacy"},
  {"continent":"North America","region":"United States","difficulty":"hard","question":"Which U.S. Supreme Court decision in 1857 denied citizenship to African Americans and inflamed sectional tensions?","choices":["Dred Scott v. Sandford","Plessy v. Ferguson","Brown v. Board of Education","Marbury v. Madison"],"answer":"Dred Scott v. Sandford"},
  {"continent":"North America","region":"Caribbean & Central America","difficulty":"hard","question":"Which 19th-century leader led independence movements across much of Spanish South America and had campaigns in the north (Bolivar)?","choices":["Simón Bolívar","José de San Martín","Miguel Hidalgo","Toussaint Louverture"],"answer":"Simón Bolívar"},

  {"continent":"South America","region":"Andes","difficulty":"easy","question":"Which empire built Machu Picchu in the Andes?","choices":["Inca Empire","Muisca","Tiahuanaco","Chavín"],"answer":"Inca Empire"},
  {"continent":"South America","region":"Amazon","difficulty":"easy","question":"Which European power colonized most of Brazil?","choices":["Portugal","Spain","France","Netherlands"],"answer":"Portugal"},
  {"continent":"South America","region":"Southern Cone","difficulty":"medium","question":"Which 19th-century Argentine leader is associated with unifying the country and serving as its first president?","choices":["Bartolomé Mitre","San Martín","Perón","Artigas"],"answer":"Bartolomé Mitre"},
  {"continent":"South America","region":"Andes","difficulty":"medium","question":"Which leader led forces to independence in the southern part of South America (Argentina/Chile)?","choices":["José de San Martín","Simón Bolívar","Antonio José de Sucre","Bernardo O'Higgins"],"answer":"José de San Martín"},
  {"continent":"South America","region":"Amazon","difficulty":"hard","question":"Which pre-Columbian culture in present-day Colombia was renowned for gold-working and the legend of El Dorado?","choices":["Muisca","Tiwanaku","Mapuche","Chibcha"],"answer":"Muisca"},
  {"continent":"South America","region":"Southern Cone","difficulty":"hard","question":"Which 20th-century military dictatorship in Argentina was responsible for the "Disappeared" during the Dirty War?","choices":["National Reorganization Process","Pinochet regime","Brazilian military government","Peruvian Sendero"],"answer":"National Reorganization Process"},

  {"continent":"Oceania","region":"Australia","difficulty":"easy","question":"Which people inhabited Australia for tens of thousands of years before European arrival?","choices":["Aboriginal Australians","Maori","Samoans","Tongans"],"answer":"Aboriginal Australians"},
  {"continent":"Oceania","region":"Polynesia","difficulty":"easy","question":"Which navigators from Polynesia settled and named New Zealand Aotearoa?","choices":["Māori","Aboriginal Australians","Fijians","Samoans"],"answer":"Māori"},
  {"continent":"Oceania","region":"Australia","difficulty":"medium","question":"Which event in 1901 created the Commonwealth of Australia?","choices":["Federation of Australia","Australian Gold Rush","Eureka Rebellion","Anzac Landing"],"answer":"Federation of Australia"},
  {"continent":"Oceania","region":"Melanesia","difficulty":"medium","question":"Which European explorer is credited with mapping parts of the Pacific including New Guinea in the 16th century?","choices":["Alvaro de Saavedra","James Cook","Abel Tasman","Ferdinand Magellan"],"answer":"Alvaro de Saavedra"},
  {"continent":"Oceania","region":"Polynesia","difficulty":"hard","question":"Which treaty in 1840 between some Māori chiefs and the British Crown is a foundational document for New Zealand?","choices":["Treaty of Waitangi","Treaty of Tordesillas","Treaty of Versailles","Anglo-Maori Accord"],"answer":"Treaty of Waitangi"},
  {"continent":"Oceania","region":"Melanesia","difficulty":"hard","question":"Which World War II campaign in the Pacific involved heavy fighting in places like Guadalcanal?","choices":["Guadalcanal Campaign","Battle of Midway","Battle of the Coral Sea","Leyte Gulf"],"answer":"Guadalcanal Campaign"}
]